[
  {
    "absolute_difference": 2.5,
    "claims": [
      {
        "context_snippet": "In adults with overweight or obesity, mean weight loss was 14.9% at week 68 with semaglutide 2.4 mg versus 2.4% with placebo.",
        "evidence_id": "ev_step1",
        "predicate": "weight loss",
        "source_tier": "T1",
        "source_url": "https://www.nejm.org/doi/full/10.1056/NEJMoa2032183",
        "subject": "semaglutide",
        "unit": "%",
        "value": 14.9
      },
      {
        "context_snippet": "Across 12 randomized controlled trials, semaglutide 2.4 mg ranked first for weight loss with a pooled estimate of 15.4% reduction.",
        "evidence_id": "ev_meta",
        "predicate": "weight loss",
        "source_tier": "T2",
        "source_url": "https://pmc.ncbi.nlm.nih.gov/articles/PMC9758543",
        "subject": "semaglutide",
        "unit": "%",
        "value": 15.4
      },
      {
        "context_snippet": "The semaglutide group achieved a mean weight loss of 16.0% at week 68 with intensive behavioral therapy.",
        "evidence_id": "ev_step3",
        "predicate": "weight loss",
        "source_tier": "T1",
        "source_url": "https://jamanetwork.com/journals/jama/fullarticle/2777025",
        "subject": "semaglutide",
        "unit": "%",
        "value": 16.0
      },
      {
        "context_snippet": "At week 104, the semaglutide 2.4 mg group had mean weight loss of 17.4% compared with placebo.",
        "evidence_id": "ev_step5",
        "predicate": "weight loss",
        "source_tier": "T1",
        "source_url": "https://diabetesjournals.org/care/article/45/5/XXX",
        "subject": "semaglutide",
        "unit": "%",
        "value": 17.4
      }
    ],
    "predicate": "weight loss",
    "recommended_action": "Disclose both values with their source tiers in the final report. If one source is T1 (RCT) and another is T5 (industry), note the authority gap alongside the numeric gap.",
    "relative_difference": 0.1678,
    "severity": "medium",
    "subject": "semaglutide"
  }
]
