{
 "status": "abort_four_role_release_held",
 "report_redaction_error": null,
 "report_redaction": {
  "already_absent_claim_ids": [],
  "redacted_claim_ids": [
   "01-003-1b438c6f",
   "01-006-c177ab46",
   "01-008-7a9b4beb",
   "01-011-9a6a61c3",
   "01-012-dbba1582",
   "01-014-e1c22bc1",
   "01-015-120e6bde",
   "04-001-fb17fd8a",
   "04-002-16dc8215"
  ],
  "redacted_count": 9
 },
 "final_verdicts": {
  "00-000-4c4e0acd": "VERIFIED",
  "00-001-2b0d902e": "VERIFIED",
  "00-002-4c12a16c": "VERIFIED",
  "00-003-21b1583e": "VERIFIED",
  "00-004-38d91101": "VERIFIED",
  "00-005-bd989d4b": "VERIFIED",
  "00-006-944bd889": "VERIFIED",
  "00-007-18c780c5": "VERIFIED",
  "00-008-094631ab": "VERIFIED",
  "00-009-5c80d74b": "VERIFIED",
  "00-010-1cf9025a": "VERIFIED",
  "00-011-147dd601": "VERIFIED",
  "00-012-18386f2c": "VERIFIED",
  "00-013-508f6f4b": "VERIFIED",
  "00-014-648be208": "VERIFIED",
  "00-015-48dd8613": "VERIFIED",
  "00-016-69000482": "VERIFIED",
  "00-017-0c5bf638": "VERIFIED",
  "00-018-a2b7aad2": "VERIFIED",
  "00-019-59b4f613": "VERIFIED",
  "00-020-b87a0ec9": "VERIFIED",
  "00-021-3ffd2f06": "VERIFIED",
  "00-022-9ec14a9b": "VERIFIED",
  "01-000-39e66499": "VERIFIED",
  "01-001-27fdb4a5": "VERIFIED",
  "01-002-3a3f2cb1": "VERIFIED",
  "01-003-1b438c6f": "UNSUPPORTED",
  "01-004-8d024662": "VERIFIED",
  "01-005-4a461eb2": "VERIFIED",
  "01-006-c177ab46": "UNSUPPORTED",
  "01-007-38c581c2": "VERIFIED",
  "01-008-7a9b4beb": "UNSUPPORTED",
  "01-009-3623d162": "VERIFIED",
  "01-010-235f3da0": "VERIFIED",
  "01-011-9a6a61c3": "UNSUPPORTED",
  "01-012-dbba1582": "UNSUPPORTED",
  "01-013-ed6b9985": "VERIFIED",
  "01-014-e1c22bc1": "UNSUPPORTED",
  "01-015-120e6bde": "UNSUPPORTED",
  "01-016-8c68fd74": "VERIFIED",
  "03-000-117bc8e8": "VERIFIED",
  "03-001-c5f53f2b": "VERIFIED",
  "03-002-8f59cb64": "VERIFIED",
  "03-003-7599dd39": "VERIFIED",
  "04-000-f394a6ec": "VERIFIED",
  "04-001-fb17fd8a": "UNSUPPORTED",
  "04-002-16dc8215": "UNSUPPORTED",
  "04-003-4b94275c": "VERIFIED",
  "04-004-d47ccb87": "VERIFIED",
  "04-005-7a264bdd": "VERIFIED",
  "05-000-95e2a97f": "VERIFIED",
  "05-001-4bbca493": "VERIFIED",
  "05-002-ec59e504": "VERIFIED",
  "05-003-b9edff21": "VERIFIED",
  "05-004-dadf0a0e": "VERIFIED"
 },
 "needs_rewrite": [
  "01-003-1b438c6f",
  "01-006-c177ab46",
  "01-008-7a9b4beb",
  "01-011-9a6a61c3",
  "01-012-dbba1582",
  "01-014-e1c22bc1",
  "01-015-120e6bde",
  "04-002-16dc8215"
 ],
 "held_reasons": [
  "d8_unsupported_residual_below_coverage",
  "d8_s0_must_cover_missing:contraindications",
  "d8_s0_must_cover_missing:dosing_limits",
  "d8_pending_rewrite"
 ]
}