{"content": "{\"analyses\": [{\"source_url\": \"https://www.researchgate.net/publication/357283172_A_comparison_of_evolution_of_adhesion_mechanisms_and_strength_post_damp-heat_aging_for_a_range_of_VA_content_in_EVA_encapsulant_with_photovoltaic_backsheet\", \"source_title\": \"A comparison of evolution of adhesion mechanisms and strength ...\", \"source_type\": \"other\", \"source_quality\": 0.0, \"overall_relevance\": 0.0, \"year\": 0, \"authors\": [], \"venue\": \"\", \"doi\": \"\", \"atomic_facts\": [], \"evidence_summary\": \"INSUFFICIENT_CONTENT\"}]}", "input_tokens": 6460, "output_tokens": 128}